obrewin-0.0.1.dist-info/METADATA
obrewin-0.0.1.dist-info/WHEEL
obrewin-0.0.1.dist-info/license_files/LICENSE
obrewin-0.0.1.dist-info/license_files/LICENSE
obrewin/__init__.py
obrewin/core.pyi
obrewin/core.cpython-311-x86_64-linux-gnu.so
obrewin-0.0.1.dist-info/RECORD
