Metadata-Version: 2.1
Name: obrewin
Version: 0.0.1
Classifier: Programming Language :: Rust
Classifier: Programming Language :: Python :: Implementation :: CPython
Classifier: Development Status :: 2 - Pre-Alpha
Classifier: Intended Audience :: Financial and Insurance Industry
License-File: LICENSE
License-File: LICENSE
Summary: A quantitative trading framework
Author: Minsung Kim <spongbob9876@naver.com>
Author-email: Minsung Kim <spongbob9876@naver.com>
Requires-Python: >=3.11
Project-URL: repository, https://github.com/McDic/Obrewin
